simple_file_user/File.py
simple_file_user/__init__.py
simple_file_user-0.2.1.dist-info/LICENSE
simple_file_user-0.2.1.dist-info/METADATA
simple_file_user-0.2.1.dist-info/WHEEL
simple_file_user-0.2.1.dist-info/top_level.txt
simple_file_user-0.2.1.dist-info/RECORD
