Metadata-Version: 2.1
Name: simple-file-user
Version: 0.2.1
Summary: Package for easy working with files.
Author-email: internetstalcker@yandex.ru
License: MIT
Project-URL: Homepage, https://github.com/InternetStalker/Simple_file_user
Project-URL: Русскоязычная документация, https://zen.yandex.ru/media/id/60856790ae47bf185f78b82d/zdravstvuite-eto-ne-statia-a-dokumentaciia-k-moemu-paketu-v-pypi-608f77907ffcba2d9e3b78fc?&
Keywords: files file
Platform: UNKNOWN
Classifier: License :: OSI Approved :: MIT License
Classifier: Operating System :: Microsoft :: Windows
Classifier: Programming Language :: Python :: 3
Classifier: Topic :: Software Development :: Libraries :: Python Modules
Classifier: Topic :: Utilities
License-File: LICENSE
